spml2/__init__.py
spml2/cli.py
spml2/core.py
spml2/feature_importances.py
spml2/options.py
spml2/parque_utils.py
spml2/utils.py
spml2/utils_init.py
spml2/web.py
spml2/data/__init__.py
spml2/data/abstract.py
spml2/data/processing.py
spml2/models/__init__.py
spml2/models/base.py
spml2/plots/__init__.py
spml2/plots/plot_roc.py
spml2/plots/shap_local.py
spml2/templates_content/main_.py
spml2/templates_content/models_.py
spml2/templates_content/options_.py
spml2/utils/__init__.py
spml2/utils/general.py
spml2/utils/parque_utils.py
spml2/utils/utils_hash.py
spml2/utils/utils_init.py
spml2_mltools-1.0.41.dist-info/METADATA
spml2_mltools-1.0.41.dist-info/WHEEL
spml2_mltools-1.0.41.dist-info/entry_points.txt
spml2_mltools-1.0.41.dist-info/licenses/LICENSE
spml2_mltools-1.0.41.dist-info/RECORD
